minicv/Colors.py
minicv/Images.py
minicv/__init__.py
minicv-1.0.3.dist-info/METADATA
minicv-1.0.3.dist-info/WHEEL
minicv-1.0.3.dist-info/top_level.txt
minicv-1.0.3.dist-info/RECORD
